pysqlrecon/__init__.py
pysqlrecon/__main__.py
pysqlrecon/lib/__init__.py
pysqlrecon/lib/clr.py
pysqlrecon/lib/exceptions.py
pysqlrecon/lib/module.py
pysqlrecon/lib/query.py
pysqlrecon/lib/sccm.py
pysqlrecon/lib/sqlagent.py
pysqlrecon/logger.py
pysqlrecon/modules/__init__.py
pysqlrecon/modules/adsi.py
pysqlrecon/modules/agentcmd.py
pysqlrecon/modules/agentstatus.py
pysqlrecon/modules/checkrpc.py
pysqlrecon/modules/clr.py
pysqlrecon/modules/columns.py
pysqlrecon/modules/databases.py
pysqlrecon/modules/disableclr.py
pysqlrecon/modules/disableole.py
pysqlrecon/modules/disablerpc.py
pysqlrecon/modules/disablexp.py
pysqlrecon/modules/enableclr.py
pysqlrecon/modules/enableole.py
pysqlrecon/modules/enablerpc.py
pysqlrecon/modules/enablexp.py
pysqlrecon/modules/impersonate.py
pysqlrecon/modules/info.py
pysqlrecon/modules/links.py
pysqlrecon/modules/olecmd.py
pysqlrecon/modules/query.py
pysqlrecon/modules/rows.py
pysqlrecon/modules/sample.py
pysqlrecon/modules/sccm/__init__.py
pysqlrecon/modules/sccm/addadmin.py
pysqlrecon/modules/sccm/credentials.py
pysqlrecon/modules/sccm/logons.py
pysqlrecon/modules/sccm/removeadmin.py
pysqlrecon/modules/sccm/sites.py
pysqlrecon/modules/sccm/taskdata.py
pysqlrecon/modules/sccm/tasklist.py
pysqlrecon/modules/sccm/users.py
pysqlrecon/modules/search.py
pysqlrecon/modules/smb.py
pysqlrecon/modules/tables.py
pysqlrecon/modules/users.py
pysqlrecon/modules/whoami.py
pysqlrecon/modules/xpcmd.py
pysqlrecon-0.3.0.dist-info/LICENSE
pysqlrecon-0.3.0.dist-info/METADATA
pysqlrecon-0.3.0.dist-info/WHEEL
pysqlrecon-0.3.0.dist-info/entry_points.txt
pysqlrecon-0.3.0.dist-info/RECORD
