Metadata-Version: 2.1
Name: pysqlrecon
Version: 0.3.0
Summary: Offensive MSSQL Python toolkit
Home-page: https://github.com/tw1sm/pysqlrecon
Author: Matt Creel
Author-email: mcreel31@gmail.com
Requires-Python: >=3.11,<4.0
Classifier: Programming Language :: Python :: 3
Classifier: Programming Language :: Python :: 3.11
Requires-Dist: impacket (>=0.11.0,<0.12.0)
Requires-Dist: pycryptodome (>=3.20.0,<4.0.0)
Requires-Dist: rich (>=12.5.1,<13.0.0)
Requires-Dist: typer (>=0.6.1,<0.7.0)
Project-URL: Repository, https://github.com/tw1sm/pysqlrecon
